dawgz/__init__.py
dawgz/__main__.py
dawgz/schedulers.py
dawgz/utils.py
dawgz/workflow.py
dawgz-1.0.4.dist-info/licenses/LICENSE
dawgz-1.0.4.dist-info/METADATA
dawgz-1.0.4.dist-info/WHEEL
dawgz-1.0.4.dist-info/entry_points.txt
dawgz-1.0.4.dist-info/top_level.txt
dawgz-1.0.4.dist-info/RECORD
