Metadata-Version: 2.4
Name: dawgz
Version: 1.0.4
Summary: Directed Acyclic Workflow Graph Scheduling
Author: Joeri Hermans
Author-email: François Rozet <francois.rozet@outlook.com>
Project-URL: documentation, https://github.com/francois-rozet/dawgz
Project-URL: source, https://github.com/francois-rozet/dawgz
Project-URL: tracker, https://github.com/francois-rozet/dawgz/issues
Keywords: workflow,scheduling,slurm,hpc
Classifier: Intended Audience :: Developers
Classifier: Intended Audience :: Science/Research
Classifier: License :: OSI Approved :: MIT License
Classifier: Natural Language :: English
Classifier: Operating System :: OS Independent
Classifier: Programming Language :: Python :: 3
Requires-Python: >=3.8
License-File: LICENSE
Requires-Dist: cloudpickle>=2.0.0
Requires-Dist: tabulate>=0.8.0
Provides-Extra: lint
Requires-Dist: ruff==0.9.9; extra == "lint"
Dynamic: license-file
